openctp_ctp_669/__about__.py
openctp_ctp_669/__init__.py
openctp_ctp_669/thostmduserapi.py
openctp_ctp_669/thosttraderapi.py
openctp_ctp_669/_thostmduserapi.so
openctp_ctp_669-1.0.2.dist-info/METADATA
openctp_ctp_669-1.0.2.dist-info/WHEEL
openctp_ctp_669-1.0.2.dist-info/licenses/LICENSE
openctp_ctp_669-1.0.2.dist-info/RECORD
